iker_package_calc_v2/calc.py
iker_package_calc_v2/const.py
iker_package_calc_v2-0.0.1.dist-info/METADATA
iker_package_calc_v2-0.0.1.dist-info/WHEEL
iker_package_calc_v2-0.0.1.dist-info/licenses/LICENSE
iker_package_calc_v2-0.0.1.dist-info/RECORD
