Metadata-Version: 2.4
Name: iker-package-calc-v2
Version: 0.0.1
Summary: Ejemplo de como crear un paquete
Project-URL: Homepage, https://github.com/Torponcito/Package
Project-URL: Bug Tracker, https://github.com/Torponcito/Package/issues
Author-email: Torponcito <ikermaria.estudios@gmail.com>
License: MIT License
License-File: LICENSE
Classifier: License :: OSI Approved :: MIT License
Classifier: Operating System :: OS Independent
Classifier: Programming Language :: Python :: 3
Requires-Python: >=3.9
